ezdecs.py
eztools.py
ezdecs-1.0.0.dist-info/METADATA
ezdecs-1.0.0.dist-info/WHEEL
ezdecs-1.0.0.dist-info/top_level.txt
ezdecs-1.0.0.dist-info/RECORD
