Metadata-Version: 2.1
Name: ezdecs
Version: 1.0.0
Summary: Some decorators that simplify Python code
Home-page: https://github.com/none-None1/ezdecs
Author: None1
Keywords: decorator,easy
Classifier: Intended Audience :: Developers
Classifier: Programming Language :: Python :: 3
Classifier: Programming Language :: Python :: 2
